odoo/addons/base_url/README.rst
odoo/addons/base_url/__init__.py
odoo/addons/base_url/__manifest__.py
odoo/addons/base_url/models/__init__.py
odoo/addons/base_url/models/abstract_url.py
odoo/addons/base_url/models/url_url.py
odoo/addons/base_url/security/ir.model.access.csv
odoo/addons/base_url/tests/__init__.py
odoo/addons/base_url/tests/models.py
odoo/addons/base_url/tests/models_mixin.py
odoo/addons/base_url/tests/test_abstract_url.py
odoo/addons/base_url/views/url_view.xml
odoo12_addon_base_url-12.0.0.2.0.dist-info/METADATA
odoo12_addon_base_url-12.0.0.2.0.dist-info/WHEEL
odoo12_addon_base_url-12.0.0.2.0.dist-info/top_level.txt
odoo12_addon_base_url-12.0.0.2.0.dist-info/RECORD
