Metadata-Version: 2.1
Name: odoo12-addon-base-url
Version: 12.0.0.2.0
Summary: keep history of url for products & categories
Home-page: https://github.com/shopinvader
Author: Akretion, ACSONE SA/NV
License: AGPL-3
Platform: UNKNOWN
Classifier: Programming Language :: Python
Classifier: Framework :: Odoo
Classifier: License :: OSI Approved :: GNU Affero General Public License v3
Requires-Python: >=3.5
Requires-Dist: odoo (<12.1dev,>=12.0a)
Requires-Dist: python-slugify (>=3.0.2)
